{
  "_fv": 6,
  "_type": "recipe",
  "definition": {
    "recipeType": "Crafting",
    "xpReward": 0.0,
    "recipeRetstackSize": 1,
    "group": "knives",
    "recipeShapeless": false,
    "recipeSlots": [
      {
        "value": "Items.DIAMOND"
      },
      {
        "value": "Items.STICK"
      },
      {
        "value": ""
      },
      {
        "value": "Items.DIAMOND"
      },
      {
        "value": "Items.STICK"
      },
      {
        "value": ""
      },
      {
        "value": ""
      },
      {
        "value": "Items.STICK"
      },
      {
        "value": ""
      }
    ],
    "recipeReturnStack": {
      "value": "CUSTOM:DiamondKnife"
    },
    "name": "r_diamond_knife",
    "namespace": "mod"
  }
}